furiosa/quantizer/__init__.py
furiosa/quantizer/calibrator.py
furiosa/quantizer/editor.py
furiosa/quantizer/git_version.txt
furiosa/quantizer/py.typed
furiosa_quantizer-0.10.2.dist-info/WHEEL
furiosa_quantizer-0.10.2.dist-info/METADATA
furiosa_quantizer-0.10.2.dist-info/RECORD
